LICENSE
MANIFEST.in
NOTICE
README.md
install.json
package.json
pyproject.toml
setup.py
tsconfig.json
tsconfig.test.json
amazon_q_developer_jupyterlab_ext/__init__.py
amazon_q_developer_jupyterlab_ext/constants.py
amazon_q_developer_jupyterlab_ext/exceptions.py
amazon_q_developer_jupyterlab_ext/handlers.py
amazon_q_developer_jupyterlab_ext/utils.py
amazon_q_developer_jupyterlab_ext.egg-info/PKG-INFO
amazon_q_developer_jupyterlab_ext.egg-info/SOURCES.txt
amazon_q_developer_jupyterlab_ext.egg-info/dependency_links.txt
amazon_q_developer_jupyterlab_ext.egg-info/not-zip-safe
amazon_q_developer_jupyterlab_ext.egg-info/requires.txt
amazon_q_developer_jupyterlab_ext.egg-info/top_level.txt
amazon_q_developer_jupyterlab_ext/auth/__init__.py
amazon_q_developer_jupyterlab_ext/auth/sso_auth_manager.py
amazon_q_developer_jupyterlab_ext/client/__init__.py
amazon_q_developer_jupyterlab_ext/client/codewhisperer/__init__.py
amazon_q_developer_jupyterlab_ext/client/codewhisperer/client_config.py
amazon_q_developer_jupyterlab_ext/client/codewhisperer/client_manager.py
amazon_q_developer_jupyterlab_ext/client/codewhisperer/file_cache_manager.py
amazon_q_developer_jupyterlab_ext/client/codewhisperer/iam_client_config.py
amazon_q_developer_jupyterlab_ext/client/codewhisperer/iam_client_manager.py
amazon_q_developer_jupyterlab_ext/client/codewhisperer/sso_client_config.py
amazon_q_developer_jupyterlab_ext/client/codewhisperer/sso_client_manager.py
amazon_q_developer_jupyterlab_ext/client/glue/__init__.py
amazon_q_developer_jupyterlab_ext/client/glue/client.py
amazon_q_developer_jupyterlab_ext/client/sagemaker/client.py
amazon_q_developer_jupyterlab_ext/client/service_models/bearer/2022-11-11/service-2.json
amazon_q_developer_jupyterlab_ext/client/service_models/glue/2017-03-31/service-2.json
amazon_q_developer_jupyterlab_ext/client/service_models/sagemaker/2017-07-24/service-2.json
amazon_q_developer_jupyterlab_ext/client/service_models/sigv4/2022-06-15/service-2.json
amazon_q_developer_jupyterlab_ext/client/service_models/telemetry/2017-07-25/service-2.json
amazon_q_developer_jupyterlab_ext/client/telemetry/__init__.py
amazon_q_developer_jupyterlab_ext/client/telemetry/telemetry.py
amazon_q_developer_jupyterlab_ext/env/__init__.py
amazon_q_developer_jupyterlab_ext/env/environment.py
